redvid/__init__.py
redvid/__main__.py
redvid/redvid.py
redvid/requestmaker.py
redvid/tools.py
redvid-2.0.6.dist-info/LICENSE
redvid-2.0.6.dist-info/METADATA
redvid-2.0.6.dist-info/WHEEL
redvid-2.0.6.dist-info/entry_points.txt
redvid-2.0.6.dist-info/top_level.txt
redvid-2.0.6.dist-info/RECORD
