Metadata-Version: 2.1
Name: redvid
Version: 2.0.6
Summary: Smart downloader for Reddit hosted videos
Home-page: https://github.com/elmoiv/redvid
Author: Khaled El-Morshedy
Author-email: elmoiv@yahoo.com
License: GPL-v3.0
Classifier: Programming Language :: Python :: 3
Classifier: License :: OSI Approved :: GNU General Public License v3 (GPLv3)
Classifier: Operating System :: OS Independent
Requires-Python: >=3.4
License-File: LICENSE
Requires-Dist: requests
